{
    "carID": "c00616",
    "cr": 417,
    "make": "Kia",
    "model": "K5 EX",
    "modelYear": 2021,
    "country": "KR",
    "topSpeed": 128,
    "0to60": 7.8,
    "handling": 75,
    "driveType": "FWD",
    "tyreType": "Standard",
    "tags": ["Rest of The World"],
    "isPrize": false,
    "weight": 1478,
    "gc": "Medium",
    "seatCount": 5,
    "bodyStyle": "Sedan",
    "tcs": true,
    "abs": true,
    "enginePos": "Front",
    "fuelType": "Petrol",
    "mra": 56.52,
    "ola": 71.79,
    "description": "Called the \"sportiest\" sedan by Forbes.",
    "racehud": "https://file.garden/ZmdgDS5GsALKuOXo/Cards/0in/KiaK5EX(2021).png",
    "creator": "Keanny",
    "hiddenTag": [""]
}
