{
    "carID": "c00971",
    "cr": 260,
    "make": "Opel",
    "model": "Astra 1.6i GLS",
    "modelYear": 1991,
    "country": "DE",
    "topSpeed": 118,
    "0to60": 10.7,
    "handling": 68,
    "driveType": "FWD",
    "tyreType": "Standard",
    "tags": [],
    "isPrize": false,
    "weight": 1045,
    "gc": "Medium",
    "seatCount": 5,
    "bodyStyle": "Hatchback",
    "tcs": true,
    "abs": true,
    "enginePos": "Front",
    "fuelType": "Petrol",
    "mra": 36.77,
    "ola": 71.03,
    "description": "Replacement for the everlasting Kadett.",
     "333TopSpeed": 122,
    "3330to60": 10.2,
    "333Handling": 70,
    "666TopSpeed": 127,
    "6660to60": 9.6,
    "666Handling": 72,
    "996TopSpeed": 131,
    "9960to60": 9.1,
    "996Handling": 72,
    "969TopSpeed": 131,
    "9690to60": 9.6,
    "969Handling": 75,
    "699TopSpeed": 127,
    "6990to60": 9.1,
    "699Handling": 75,
    "racehud": "https://file.garden/ZSrBMiDRyR84aPJp/Placeholder.png",
    "creator": "Connor"
}