{
    "carID": "c01036",
    "cr": 140,
    "make": "Plymouth",
    "model": "Voyager LE",
    "modelYear": 1984,
    "country": "US",
    "topSpeed": 94,
    "0to60": 14,
    "handling": 61,
    "driveType": "FWD",
    "tyreType": "Standard",
    "tags": ["OG"],
    "isPrize": false,
    "weight": 1432,
    "gc": "Medium",
    "seatCount": 7,
    "bodyStyle": "Other",
    "tcs": false,
    "abs": false,
    "enginePos": "Front",
    "fuelType": "Petrol",
    "mra": 14.47,
    "ola": 62.86,
    "description": "",
    "racehud": "https://file.garden/ZSrBMiDRyR84aPJp/Cards(normal)/0in/PlymouthVoyagerLE(1984).png",
    "creator": "Andu",
    "hiddenTag": [""]
}
