{
    "carID": "c01153",
    "cr": 572,
    "make": ["Ruf","Porsche"],
    "model": "3400 S",
    "modelYear": 1999,
    "country": "DE",
    "topSpeed": 173,
    "0to60": 5.1,
    "handling": 83,
    "driveType": "RWD",
    "tyreType": "Performance",
    "tags": ["Tuner","OG"],
    "isPrize": false,
    "weight": 1260,
    "gc": "Low",
    "seatCount": 2,
    "bodyStyle": "Convertible",
    "tcs": true,
    "abs": true,
    "enginePos": "Middle",
    "fuelType": "Petrol",
    "mra": 63.51,
    "ola": 85.11,
    "description": "Ruf technicians performed a heart transplant by substituting the stock powerplant with a Ruf massaged 3.4L flat 6 sourced from the roadster's big brother.",
    "racehud": "https://file.garden/aFBkIPmb4DlYDcyR/Cars/0in/Ruf3400S(1999).png",
    "creator": "Bnuuy",
    "hiddenTag": [""]
}
