{
    "rq": 79,
    "make": "Tesla",
    "model": "Model 3 Dual Motor Long Range",
    "modelYear": 2018,
    "country": "US",
    "topSpeed": 145,
    "0to60": 4.2,
    "handling": 80,
    "driveType": "4WD",
    "tyreType": "Standard",
    "tags": [
        "Eco-Friendly"
    ],
    "isPrize": false,
    "weight": 1847,
    "gc": "Medium",
    "seatCount": 5,
    "bodyStyle": "Sedan",
    "tcs": true,
    "abs": true,
    "enginePos": "Mixed",
    "fuelType": "Electric",
    "mra": 77.86,
    "ola": 88.19,
    "description": "On Christmas 2019, this car's rear inverter short circuited and stranded Car & Driver's crew when parked. This was the first time something like this happened during their long-term testing. This, alongside many other faults including a relay attack vulnerability that lets the attacker control the car remotely, tarnished the car's (and by extension Tesla and Elon Musk's) reputation.",
    "card": "https://media.discordapp.net/attachments/819199720249360384/858544280692064277/tesla_model_3_dual_motor_long_range.png",
    "333TopSpeed": 149,
    "3330to60": 4,
    "333Handling": 83,
    "666TopSpeed": 152,
    "6660to60": 3.8,
    "666Handling": 85,
    "996TopSpeed": 151,
    "9960to60": 3.6,
    "996Handling": 85,
    "969TopSpeed": 156,
    "9690to60": 3.8,
    "969Handling": 89,
    "699TopSpeed": 152,
    "6990to60": 3.6,
    "699Handling": 89,
    "racehud": "https://media.discordapp.net/attachments/995376525119586356/1002951371164762212/model_3_dual.jpg",
    "creator": "Keanny"
}