{
    "carID": "c01381",
    "cr": 300,
    "make": "Volkswagen",
    "model": "Jetta TDI Cup Edition",
    "modelYear": 2010,
    "country": "DE",
    "topSpeed": 130,
    "0to60": 9.3,
    "handling": 76,
    "driveType": "FWD",
    "tyreType": "Performance",
    "tags": [],
    "isPrize": false,
    "weight": 1460,
    "gc": "Medium",
    "seatCount": 5,
    "bodyStyle": "Sedan",
    "tcs": true,
    "abs": true,
    "enginePos": "Front",
    "fuelType": "Diesel",
    "mra": 63.27,
    "ola": 73.12,
    "description": "Let’s be honest, who wouldn’t want a sporty version of a cheating scandal diesel?",
    "racehud": "https://file.garden/ZSrBMiDRyR84aPJp/Cards(normal)/0in/VolkswagenJettaTDICupEdition(2010).png",
    "creator": "Andu",
    "hiddenTag": [""]
}
