{
    "rq": 61,
    "make": "Mitsubishi",
    "model": "Lancer Evolution II GSR",
    "modelYear": 1994,
    "country": "JP",
    "topSpeed": 112,
    "0to60": 5.2,
    "handling": 79,
    "driveType": "4WD",
    "tyreType": "Performance",
    "tags": ["Street Racer","The Japanese Odyssey"],
    "isPrize": false,
    "weight": 1180,
    "gc": "Medium",
    "seatCount": 5,
    "bodyStyle": "Sedan",
    "tcs": true,
    "abs": true,
    "enginePos": "Front",
    "fuelType": "Petrol",
    "mra": 62.65,
    "ola": 73.08,
    "description": "None.",
    "card": "https://cdn.discordapp.com/attachments/819199720249360384/913406673161424896/evo2gsr.png",
    "333TopSpeed": 117,
    "3330to60": 4.9,
    "333Handling": 82,
    "666TopSpeed": 121,
    "6660to60": 4.7,
    "666Handling": 84,
    "996TopSpeed": 126,
    "9960to60": 4.4,
    "996Handling": 84,
    "969TopSpeed": 126,
    "9690to60": 4.7,
    "969Handling": 88,
    "699TopSpeed": 121,
    "6990to60": 4.4,
    "699Handling": 88,
    "racehud": "https://cdn.discordapp.com/attachments/995376525119586356/996024980355686440/lanevoiigsr.png",
    "creator": "Bnuuy"
}