{
    "rq": 78,
    "make": "Mitsubishi",
    "model": "Lancer Evolution IX FQ-300",
    "modelYear": 2005,
    "country": "JP",
    "topSpeed": 157,
    "0to60": 4.4,
    "handling": 88,
    "driveType": "4WD",
    "tyreType": "Performance",
    "tags": ["Street Racer","The Japanese Odyssey"],
    "isPrize": false,

    "weight": 1400,
    "gc": "Medium",
    "seatCount": 5,
    "bodyStyle": "Sedan",
    "tcs": true,
    "abs": true,
    "enginePos": "Front",
    "fuelType": "Petrol",
    "mra": 62.86,
    "ola": 77.27,
    "description": "Card by Bnuuy.",

    "card": "https://cdn.discordapp.com/attachments/819199720249360384/948546476185903155/evo9fq300.png",
    "racehud000": "https://cdn.discordapp.com/attachments/819200156623962122/948546933528596481/evo9fq300.png",
    "racehud333": "https://cdn.discordapp.com/attachments/819200156623962122/948546939178348574/evo9fq300333.png",
    "racehud666": "https://cdn.discordapp.com/attachments/819200156623962122/948546946811965530/evo9fq300666.png",
    "racehud996": "https://cdn.discordapp.com/attachments/819200156623962122/948546969465393203/evo9fq300996.png",
    "racehud969": "https://cdn.discordapp.com/attachments/819200156623962122/948546966248390716/evo9fq300969.png",
    "racehud699": "https://cdn.discordapp.com/attachments/819200156623962122/948546955372560415/evo9fq300699.png",

    "333TopSpeed": 160,
    "3330to60": 4.2,
    "333Handling": 91,

    "666TopSpeed": 164,
    "6660to60": 4.0,
    "666Handling": 94,

    "996TopSpeed": 167,
    "9960to60": 3.7,
    "996Handling": 94,

    "969TopSpeed": 167,
    "9690to60": 4.0,
    "969Handling": 98,

    "699TopSpeed": 164,
    "6990to60": 3.7,
    "699Handling": 98
}