{
    "carID": "c01891",
    "cr": 437,
    "make": "Toyota",
    "model": "Corolla T-Sport Compressor",
    "modelYear": 2004,
    "country": "JP",
    "topSpeed": 146,
    "0to60": 6.8,
    "handling": 77,
    "driveType": "FWD",
    "tyreType": "Performance",
    "tags": ["Hot Hatch","The Japanese Odyssey"],
    "isPrize": false,
    "weight": 1315,
    "gc": "Medium",
    "seatCount": 5,
    "bodyStyle": "Hatchback",
    "tcs": true,
    "abs": true,
    "enginePos": "Front",
    "fuelType": "Petrol",
    "mra": 66.67,
    "ola": 79.41,
    "description": "Limited Edition version of the T-Sport added a supercharger found in the Lotus Exige 240R.",
     "333TopSpeed": 150,
    "3330to60": 6.5,
    "333Handling": 80,
    "666TopSpeed": 153,
    "6660to60": 6.1,
    "666Handling": 82,
    "996TopSpeed": 157,
    "9960to60": 5.8,
    "996Handling": 82,
    "969TopSpeed": 157,
    "9690to60": 6.1,
    "969Handling": 85,
    "699TopSpeed": 153,
    "6990to60": 5.8,
    "699Handling": 85,
    "racehud": "https://file.garden/ZmdgDS5GsALKuOXo/Cards/0in/ToyotaCorollaTSportCompressor(2004).png",
    "creator": "Connor"
}
