{
    "rq": 22,
    "make": "Suzuki",
    "model": "Hustler Hybrid X Turbo 4WD",
    "modelYear": 2020,
    "country": "JP",
    "topSpeed": 87,
    "0to60": 14,
    "handling": 67,
    "driveType": "4WD",
    "tyreType": "Standard",
    "tags": [
        "Kei Car",
        "Eco-Friendly",
        "The Japanese Odyssey"
    ],
    "isPrize": false,
    "weight": 870,
    "gc": "High",
    "seatCount": 5,
    "bodyStyle": "Hatchback",
    "tcs": true,
    "abs": true,
    "enginePos": "Front",
    "fuelType": "Hybrid",
    "mra": 8.91,
    "ola": 55.71,
    "description": "Do the hustle. Card by Macan.",
    "card": "https://cdn.discordapp.com/attachments/819199720249360384/969596832621674616/Hustler_Hybrid_X_Turbo_4WD_20.png",
    "333TopSpeed": 93,
    "3330to60": 13.3,
    "333Handling": 68,
    "666TopSpeed": 99,
    "6660to60": 12.6,
    "666Handling": 70,
    "996TopSpeed": 105,
    "9960to60": 11.9,
    "996Handling": 70,
    "969TopSpeed": 105,
    "9690to60": 12.6,
    "969Handling": 73,
    "699TopSpeed": 99,
    "6990to60": 11.9,
    "699Handling": 73,
    "racehud": "https://cdn.discordapp.com/attachments/716917404868935691/997766459843428362/placeholder3.png",
    "creator": ""
}