{
    "rq": 37,
    "make": "Toyota",
    "model": "Camry XLE V6",
    "modelYear": 1996,
    "country": "JP",
    "topSpeed": 128,
    "0to60": 8.4,
    "handling": 70,
    "driveType": "FWD",
    "tyreType": "Standard",
    "tags": [
        "The Japanese Odyssey"
    ],
    "isPrize": false,
    "weight": 1257,
    "gc": "Medium",
    "seatCount": 5,
    "bodyStyle": "Sedan",
    "tcs": true,
    "abs": true,
    "enginePos": "Front",
    "fuelType": "Petrol",
    "mra": 65,
    "ola": 76.19,
    "description": "Card by ChickenMcNuggets.",
    "card": "https://media.discordapp.net/attachments/819199720249360384/882732041144262737/camry_xle_v6.png",
    "333TopSpeed": 132,
    "3330to60": 8,
    "333Handling": 72,
    "666TopSpeed": 136,
    "6660to60": 7.6,
    "666Handling": 75,
    "996TopSpeed": 140,
    "9960to60": 7.1,
    "996Handling": 75,
    "969TopSpeed": 140,
    "9690to60": 7.6,
    "969Handling": 78,
    "699TopSpeed": 136,
    "6990to60": 7.1,
    "699Handling": 78,
    "racehud": "https://media.discordapp.net/attachments/716917404868935691/997766459843428362/placeholder3.png",
    "creator": ""
}