{
    "carID": "c02066",
    "cr": 478,
    "make": ["Mercedes-AMG","Mercedes-Benz"],
    "model": "C 43",
    "modelYear": 1997,
    "country": "DE",
    "topSpeed": 155,
    "0to60": 6.2,
    "handling": 77,
    "driveType": "RWD",
    "tyreType": "Performance",
    "tags": [],
    "isPrize": false,
    "weight": 1495,
    "gc": "Medium",
    "seatCount": 5,
    "bodyStyle": "Sedan",
    "tcs": true,
    "abs": true,
    "enginePos": "Front",
    "fuelType": "Petrol",
    "mra": 68.8,
    "ola": 82.59,
    "description": "The real Original Merc AMG.",
    "racehud": "https://file.garden/ZSrBMiDRyR84aPJp/Cards(normal)/0in/MercedesBenzC43AMG(1997).png",
    "creator": "Havvy",
    "hiddenTag": [""]
}
