{
    "carID": "c02067",
    "cr": 802,
    "make": ["Mercedes-AMG","Mercedes-Benz"],
    "model": "G 63",
    "modelYear": 2018,
    "country": "DE",
    "topSpeed": 137,
    "0to60": 4.1,
    "handling": 70,
    "driveType": "4WD",
    "tyreType": "All-Surface",
    "tags": ["Extreme Juggernaut"],
    "isPrize": false,
    "weight": 2485,
    "gc": "High",
    "seatCount": 5,
    "bodyStyle": "SUV",
    "tcs": true,
    "abs": true,
    "enginePos": "Front",
    "fuelType": "Petrol",
    "mra": 68.33,
    "ola": 73.17,
    "description": "New Year, New Me!",
"333TopSpeed": 141,
"3330to60": 3.9,
"333Handling": 72,

"666TopSpeed": 145,
"6660to60": 3.7,
"666Handling": 75,

"699TopSpeed": 145,
"6990to60": 3.5,
"699Handling": 78,

"969TopSpeed": 148,
"9690to60": 3.7,
"969Handling": 78,

"996TopSpeed": 148,
"9960to60": 3.5,
"996Handling": 75,
    "racehud": "https://file.garden/ZSrBMiDRyR84aPJp/Cards(normal)/0in/MercedesAMGG63(2018).png",
    "creator": "Havvy",
    "hiddenTag": [""]
}
