{
    "rq": 50,
    "make": "ZAP",
    "model": "Alias Concept",
    "modelYear": 2007,
    "country": "US",
    "topSpeed": 156,
    "0to60": 5.7,
    "handling": 81,
    "driveType": "FWD",
    "tyreType": "Performance",
    "tags": [
        "Unique",
        "Concept"
    ],
    "isPrize": false,
    "weight": 1200,
    "gc": "Low",
    "seatCount": 3,
    "bodyStyle": "Coupe",
    "tcs": true,
    "abs": true,
    "enginePos": "Mixed",
    "fuelType": "Petrol",
    "mra": 55.88,
    "ola": 80.7,
    "description": "It was supposed to beat porsches. Card by Keanny.",
    "card": "https://cdn.discordapp.com/attachments/819199720249360384/976470485242118264/zap_alias_concept.png",
    "333TopSpeed": 159,
    "3330to60": 5.4,
    "333Handling": 84,
    "666TopSpeed": 163,
    "6660to60": 5.1,
    "666Handling": 86,
    "996TopSpeed": 166,
    "9960to60": 4.8,
    "996Handling": 86,
    "969TopSpeed": 166,
    "9690to60": 5.1,
    "969Handling": 90,
    "699TopSpeed": 163,
    "6990to60": 4.8,
    "699Handling": 90,
    "racehud": "https://cdn.discordapp.com/attachments/716917404868935691/997766459843428362/placeholder3.png",
    "creator": ""
}