{
    "carID": "c02323",
    "cr": 833,
    "make": ["Zagato","Ferrari"],
    "model": "599 GTZ Nibbio",
    "modelYear": 2017,
    "country": "IT",
    "topSpeed": 205,
    "0to60": 3.3,
    "handling": 91,
    "driveType": "RWD",
    "tyreType": "Performance",
    "tags": ["Unique","Supercar"],
    "isPrize": true,
    "weight": 1690,
    "gc": "Low",
    "seatCount": 2,
    "bodyStyle": "Coupe",
    "tcs": true,
    "abs": true,
    "enginePos": "Front",
    "fuelType": "Petrol",
    "mra": 86.84,
    "ola": 72.73,
    "description": "Slightly lighter than the original but wildly different looks.",
    "racehud": "https://file.garden/ZSrBMiDRyR84aPJp/Cards(normal)/0in/Zagato599GTZNibbio(2017).png",
    "creator": "Bnuuy",
    "hiddenTag": [""]
}
