{
    "carID": "c02739",
    "cr": 374,
    "make": "Audi",
    "model": "A6 Avant 3.0 TDI multitronic",
    "modelYear": 2011,
    "country": "DE",
    "topSpeed": 139,
    "0to60": 7.6,
    "handling": 78,
    "driveType": "FWD",
    "tyreType": "Standard",
    "tags": ["Year of the Rabbit"],
    "isPrize": false,
    "weight": 1780,
    "gc": "Low",
    "seatCount": 5,
    "bodyStyle": "Wagon",
    "tcs": true,
    "abs": true,
    "enginePos": "Front",
    "fuelType": "Diesel",
    "mra": 63.87,
    "ola": 78.95,
    "description": "Just like the 2.0 TDI, just a bit faster and with an awesome 3.0 V6.",
    "racehud": "https://file.garden/ZmdgDS5GsALKuOXo/Cards/0in/AudiA6Avant3.0TDImultitronic(2011).png",
    "creator": "Lemon",
    "hiddenTag": [""]
}
