{
    "carID": "c03212",
    "cr": 857,
    "make": ["Gemballa","Ferrari"],
    "model": "MIG-U1",
    "modelYear": 2010,
    "country": "DE",
    "topSpeed": 217,
    "0to60": 3.2,
    "handling": 92,
    "driveType": "RWD",
    "tyreType": "Performance",
    "tags": ["The Tyrol Tour: Remix","Ultra Expensive","Tuner","Unique","Supercar"],
    "isPrize": false,
    "weight": 1255,
    "gc": "Low",
    "seatCount": 2,
    "bodyStyle": "Coupe",
    "tcs": true,
    "abs": true,
    "enginePos": "Middle",
    "fuelType": "Petrol",
    "mra": 100,
    "ola": 100,
    "description": "",
    "racehud": "https://file.garden/ZSrBMiDRyR84aPJp/Cards(normal)/0in/GemballaMIGU1(2010).png",
    "creator": "Bnuuy",
    "hiddenTag": [""]
}
