{
    "carID": "c03480",
    "cr": 799,
    "make": "Vector",
    "model": "Avtech WX-3R",
    "modelYear": 1993,
    "country": "US",
    "topSpeed": 217,
    "0to60": 3.7,
    "handling": 83,
    "driveType": "RWD",
    "tyreType": "Performance",
    "tags": ["Supercar","Oddity","Unique","The Americas Assault"],
    "isPrize": false,
    "weight": 1670,
    "gc": "Medium",
    "seatCount": 2,
    "bodyStyle": "Convertible",
    "tcs": false,
    "abs": false,
    "enginePos": "Middle",
    "fuelType": "Petrol",
    "mra": 99.73,
    "ola": 102.97,
    "description": "One of the most interesting automotive american stories.",
    "racehud": "https://file.garden/ZSrBMiDRyR84aPJp/Cards(normal)/0in/VectorAvtechWX3R(1993).png",
    "creator": "Biszkoptowiec",
    "hiddenTag": [""]
}
