{
    "carID": "c05632",
    "cr": 856,
    "make": "Gordon Murray Automotive",
    "model": "T.33 Spider",
    "modelYear": 2023,
    "country": "GB",
    "topSpeed": 208,
    "0to60": 3.3,
    "handling": 92,
    "driveType": "RWD",
    "tyreType": "Performance",
    "tags": ["CD 2.0: New Era", "Supercar"],
    "isPrize": false,
    "weight": 1108,
    "gc": "Low",
    "seatCount": 2,
    "bodyStyle": "Convertible",
    "tcs": true,
    "abs": true,
    "enginePos": "Middle",
    "fuelType": "Petrol",
    "mra": 105.88,
    "ola": 96.22,
    "description": "",
"333TopSpeed": 211,
"3330to60": 3.1,
"333Handling": 95,

"666TopSpeed": 213,
"6660to60": 3,
"666Handling": 98,

"699TopSpeed": 213,
"6990to60": 2.8,
"699Handling": 102,

"969TopSpeed": 216,
"9690to60": 3,
"969Handling": 102,

"996TopSpeed": 216,
"9960to60": 2.8,
"996Handling": 98,
    "racehud": "https://temporary-file-garden.link/ZmdgDS5GsALKuOXo/Cards/0in/GMAT33Spider(2023).png",
    "creator": "Bnuuy"
}