{
    "carID": "c05792",
    "cr": 639,
    "make": "Wiesmann",
    "model": "Roadster MF3",
    "modelYear": 2003,
    "country": "DE",
    "topSpeed": 158,
    "0to60": 4.6,
    "handling": 87,
    "driveType": "RWD",
    "tyreType": "Performance",
    "tags": ["CD Contenders", "Unique"],
    "isPrize": false,
    "weight": 1180,
    "gc": "Low",
    "seatCount": 2,
    "bodyStyle": "Convertible",
    "tcs": false,
    "abs": true,
    "enginePos": "Front",
    "fuelType": "Petrol",
    "mra": 73.97,
    "ola": 90.62,
    "description": "The final form of MF3 with the engine from E46 M3.",
    "333TopSpeed": 161,
    "3330to60": 4.4,
    "333Handling": 90,
    "666TopSpeed": 165,
    "6660to60": 4.1,
    "666Handling": 93,
    "699TopSpeed": 165,
    "6990to60": 3.9,
    "699Handling": 97,
    "969TopSpeed": 168,
    "9690to60": 4.1,
    "969Handling": 97,
    "996TopSpeed": 168,
    "9960to60": 3.9,
    "996Handling": 93,
    "racehud": "https://file.garden/ZmdgDS5GsALKuOXo/Cards/0in/WiesmannRoadsterMF3(2003).png",
    "creator": "Crossfire",
    "hiddenTag": [""]
}