{
    "carID": "c06715",
    "cr": 796,
    "make": "Zeekr",
    "model": "X Privilege AWD",
    "modelYear": 2023,
    "country": "CN",
    "topSpeed": 118,
    "0to60": 3.7,
    "handling": 85,
    "driveType": "4WD",
    "tyreType": "Performance",
    "tags": ["CDCCS","The Amplification of Asia","Eco-Friendly","Rest of The World"],
    "isPrize": false,
    "weight": 1990,
    "gc": "Medium",
    "seatCount": 5,
    "bodyStyle": "SUV",
    "tcs": true,
    "abs": true,
    "enginePos": "Mixed",
    "fuelType": "Electric",
    "mra": 65.45,
    "ola": 72.22,
    "description": "",
    "racehud": "https://file.garden/ZmdgDS5GsALKuOXo/Cards/0in/ZeekrXPrivilegeAWD(2023).png",
    "creator": "Connor",
    "hiddenTag": [""]
}
