{
    "carID": "c06755",
    "cr": 429,
    "make": "Toyota",
    "model": "FT-86 Concept",
    "modelYear": 2009,
    "country": "JP",
    "topSpeed": 143,
    "0to60": 6.5,
    "handling": 84,
    "driveType": "RWD",
    "tyreType": "Performance",
    "tags": ["CDCCS","The Amplification of Asia","Concept"],
    "isPrize": false,
    "weight": 1060,
    "gc": "Low",
    "seatCount": 4,
    "bodyStyle": "Coupe",
    "tcs": true,
    "abs": true,
    "enginePos": "Front",
    "fuelType": "Petrol",
    "mra": 63.89,
    "ola": 77.1,
    "description": "",
    "racehud": "https://file.garden/ZmdgDS5GsALKuOXo/Cards/0in/ToyotaFT-86Concept(2009).png",
    "creator": "Pfugs",
    "hiddenTag": [""]
}
