{
    "carID": "c06722",
    "cr": 478,
    "make": "Infiniti",
    "model": "G25x",
    "modelYear": 2011,
    "country": "JP",
    "topSpeed": 145,
    "0to60": 7.5,
    "handling": 77,
    "driveType": "4WD",
    "tyreType": "Standard",
    "tags": ["CDCCS","The Amplification of Asia"],
    "isPrize": false,
    "weight": 1700,
    "gc": "Medium",
    "seatCount": 5,
    "bodyStyle": "Sedan",
    "tcs": true,
    "abs": true,
    "enginePos": "Front",
    "fuelType": "Petrol",
    "mra": 58.55,
    "ola": 72.2,
    "description": "",

"333TopSpeed": 149,
"3330to60": 7.1,
"333Handling": 80,

"666TopSpeed": 152,
"6660to60": 6.8,
"666Handling": 82,

"699TopSpeed": 152,
"6990to60": 6.4,
"699Handling": 85,

"969TopSpeed": 156,
"9690to60": 6.8,
"969Handling": 85,

"996TopSpeed": 156,
"9960to60": 6.4,
"996Handling": 82,
    "racehud": "https://file.garden/ZmdgDS5GsALKuOXo/Cards/0in/InfinitiG25x(2011).png",
    "creator": "Kuroi",
    "hiddenTag": [""]
}