{
    "carID": "c07612",
    "cr": 1047,
    "make": "Koenigsegg",
    "model": "Chimera",
    "modelYear": 2024,
    "country": "SE",
    "topSpeed": 290,
    "0to60": 2.4,
    "handling": 96,
    "driveType": "RWD",
    "tyreType": "Performance",
    "tags": ["Ultra Expensive","Hypercar","Rest of The World","Unique","Chop Shop"],
    "isPrize": true,
    "weight": 1220,
    "gc": "Low",
    "seatCount": 2,
    "bodyStyle": "Convertible",
    "tcs": true,
    "abs": true,
    "enginePos": "Middle",
    "fuelType": "Petrol",
    "mra": 160,
    "ola": 103.69,
    "description": "",
"333TopSpeed": 292,
"3330to60": 2.3,
"333Handling": 99,

"666TopSpeed": 294,
"6660to60": 2.2,
"666Handling": 102,

"699TopSpeed": 294,
"6990to60": 2,
"699Handling": 107,

"969TopSpeed": 295,
"9690to60": 2.2,
"969Handling": 107,

"996TopSpeed": 295,
"9960to60": 2,
"996Handling": 102,
    "racehud": "https://file.garden/aFBkIPmb4DlYDcyR/Cars/0in/KoenigseggChimera(2024).png",
    "creator": "Bnuuy"
}