{
    "carID": "c07844",
    "cr": 401,
    "make": "Chrysler",
    "model": "300S",
    "modelYear": 2013,
    "country": "US",
    "topSpeed": 119,
    "0to60": 6.5,
    "handling": 75,
    "driveType": "RWD",
    "tyreType": "Performance",
    "tags": ["Liberty Showdown","Muscle Car"],
    "isPrize": false,
    "weight": 1830,
    "gc": "Medium",
    "seatCount": 5,
    "bodyStyle": "Sedan",
    "tcs": true,
    "abs": true,
    "enginePos": "Front",
    "fuelType": "Petrol",
    "mra": 66.89,
    "ola": 80.36,
    "description": "",
    "racehud": "https://file.garden/aFBkIPmb4DlYDcyR/Cars/0in/Chrysler300S(2013).png",
    "creator": "DodgeDemon",
    "hiddenTag": [""]
}
