{
    "carID": "c08300",
    "make": "Porsche",
    "model": "911 GT3 S/C Street Style Package",
    "modelYear": 2026,
    "country": "DE",
    "reference": "c08299",
    "collection": ["Event Hunter Collection 1"],
    "active" : false,
    "description": "Tick the box for the Street Style package and you access options that would usually be restricted to the Sonderwunsch (special request) programme. The car seen in the card is a perfect illustration of just how far you can take this, with it adopting the iconic grey on red theme launched on the 997 GT3 RS.",
    "racehud": "https://file.garden/aFBkIPmb4DlYDcyR/Cars/1BM/0in/Porsche911GT3SCStreetStyle.png",
    "creator": "Bnuuy",
    "hiddenTag": [""]
}