{
    "rq": 31,
    "make": "AMC",
    "model": "Javelin SST",
    "modelYear": 1968,
    "country": "US",
    "topSpeed": 117,
    "0to60": 6.9,
    "handling": 61,
    "driveType": "RWD",
    "tyreType": "Performance",
    "tags": ["Muscle Car"],
    "isPrize": false,

    "weight": 1286,
    "gc": "Medium",
    "seatCount":4,
    "bodyStyle": "Coupe",
    "tcs": false,
    "abs": false,
    "enginePos": "Front",
    "fuelType": "Petrol",
    "mra": 64.49,
    "ola": 78.26,
    "description": "Johnny’s dad says hi. Card by Johnny",

    "card": "https://cdn.discordapp.com/attachments/819199720249360384/819535315957186581/AMC-Javelin-SST.png",
    "racehud000": "https://media.discordapp.net/attachments/718097267621363744/802222398261821490/AMC-Javelin-SST.png",
    "racehud333": "https://cdn.discordapp.com/attachments/819200156623962122/819537716060094484/AMC-Javelin-SST-1-star.png",
    "racehud666": "https://cdn.discordapp.com/attachments/819200156623962122/819537720249942056/AMC-Javelin-SST-2-star.png",
    "racehud996": "https://cdn.discordapp.com/attachments/819200156623962122/819537743264612362/AMC-Javelin-SST-332.png",
    "racehud969": "https://cdn.discordapp.com/attachments/819200156623962122/819537735207223377/AMC-Javelin-SST-323.png",
    "racehud699": "https://cdn.discordapp.com/attachments/819200156623962122/819537728139034714/AMC-Javelin-SST-233.png",

    "333TopSpeed": 121,
    "3330to60": 6.6,
    "333Handling": 63,

    "666TopSpeed": 126,
    "6660to60": 6.2, 
    "666Handling": 65,

    "996TopSpeed": 130,
    "9960to60": 5.9,
    "996Handling": 65,

    "969TopSpeed": 130,
    "9690to60": 6.2,
    "969Handling": 68,

    "699TopSpeed": 126,
    "6990to60": 5.9,
    "699Handling": 68
}