{
    "rq": 27,
    "make": "Opel",
    "model": "Astra Sports Tourer 1.7 CDTI",
    "modelYear": 2009,
    "country": "DE",
    "topSpeed": 114,
    "0to60": 11.0,
    "handling": 73,
    "driveType": "FWD",
    "tyreType": "Standard",
    "tags": [],
    "isPrize": false,

    "weight": 1578,
    "gc": "Medium",
    "seatCount": 5,
    "bodyStyle": "Wagon",
    "tcs": true,
    "abs": true,
    "enginePos": "Front",
    "fuelType": "Diesel",
    "mra": 45.08,
    "ola": 69.09,
    "description": "Card by Connor",

    "card": "https://cdn.discordapp.com/attachments/819199720249360384/845753774781628426/E.OpelAstraST17CDTI.png",
    "racehud000": "https://cdn.discordapp.com/attachments/819200156623962122/845754509573619792/E.OpelAstraST17CDTI.png",
    "racehud333": "https://cdn.discordapp.com/attachments/819200156623962122/845754530036711454/E.OpelAstraST17CDTI-1.png",
    "racehud666": "https://cdn.discordapp.com/attachments/819200156623962122/845754544188162048/E.OpelAstraST17CDTI-2.png",
    "racehud996": "https://cdn.discordapp.com/attachments/819200156623962122/845754588081553408/E.OpelAstraST17CDTI-996.png",
    "racehud969": "https://cdn.discordapp.com/attachments/819200156623962122/845754573061750864/E.OpelAstraST17CDTI-969.png",
    "racehud699": "https://cdn.discordapp.com/attachments/819200156623962122/845754557639294976/E.OpelAstraST17CDTI-699.png",

    "333TopSpeed": 119,
    "3330to60": 10.5,
    "333Handling": 75,

    "666TopSpeed": 123,
    "6660to60": 9.9,
    "666Handling": 78,

    "996TopSpeed": 128,
    "9960to60": 9.4,
    "996Handling": 78,

    "969TopSpeed": 128,
    "9690to60": 9.9,
    "969Handling": 81,

    "699TopSpeed": 123,
    "6990to60": 9.4,
    "699Handling": 81
}