{
    "rq": 98,
    "make": "Porsche",
    "model": "918 Spyder",
    "modelYear": 2013,
    "country": "DE",
    "topSpeed": 214,
    "0to60": 2.4,
    "handling": 93,
    "driveType": "4WD",
    "tyreType": "Performance",
    "tags": ["Hypercar", "Eco-Friendly"],
    "isPrize": false,


    "weight": 1685,
    "gc": "Low",
    "seatCount":2,
    "bodyStyle": "Convertible",
    "tcs": true,
    "abs": true,
    "enginePos": "Middle",
    "fuelType": "Hybrid",
    "mra": 96.00,
    "ola": 83.33,
    "description": "A hybrid hypercar like no other. Two electric motors and a 9,000rpm 4.6-litre racing V8. Card by Keanny",


    "card": "https://cdn.discordapp.com/attachments/819199720249360384/819382690150088714/918_spoyder.png",
    "racehud000": "https://cdn.discordapp.com/attachments/819200156623962122/819512481834598440/918_000.jpg",
    "racehud333": "https://cdn.discordapp.com/attachments/819200156623962122/819512495789703178/918_333.jpg",
    "racehud666": "https://cdn.discordapp.com/attachments/819200156623962122/819512501968306176/918_666.jpg",
    "racehud996": "https://cdn.discordapp.com/attachments/819200156623962122/819512538034602004/918_996.jpg",
    "racehud969": "https://cdn.discordapp.com/attachments/819200156623962122/819512525829046292/918_969.jpg",
    "racehud699": "https://cdn.discordapp.com/attachments/819200156623962122/819512514105704458/918_699.jpg",


    "333TopSpeed": 216,
    "3330to60": 2.3,
    "333Handling": 96,

    "666TopSpeed": 219,
    "6660to60": 2.2, 
    "666Handling": 99,

    "996TopSpeed": 221,
    "9960to60": 2.0,
    "996Handling": 99,

    "969TopSpeed": 221,
    "9690to60": 2.2,
    "969Handling": 103,

    "699TopSpeed": 219,
    "6990to60": 2.0,
    "699Handling": 103
}
