{
    "rq": 20,
    "make": "Kia",
    "model": "Soul EV",
    "modelYear": 2016,
    "country": "KR",
    "topSpeed": 92,
    "0to60": 9.7,
    "handling": 68,
    "driveType": "FWD",
    "tyreType": "Standard",
    "tags": ["Eco-Friendly"],
    "isPrize": false,

    "weight": 1495,
    "gc": "Medium",
    "seatCount": 5,
    "bodyStyle": "Hatchback",
    "tcs": true,
    "abs": true,
    "enginePos": "Front",
    "fuelType": "Electric",
    "mra": 0.00,
    "ola": 63.92,
    "description": "",

    "card": "https://cdn.discordapp.com/attachments/715782088271331398/746959913322020864/SoulEV16.png",
    "racehud000": "https://cdn.discordapp.com/attachments/718097267621363744/746321904276733962/SoulEVStock.png",
    "racehud333": "https://cdn.discordapp.com/attachments/718097267621363744/746321931896094730/SoulEV333.png",
    "racehud666": "https://cdn.discordapp.com/attachments/718097267621363744/746321952846643271/SoulEV666.png",
    "racehud996": "",
    "racehud969": "https://cdn.discordapp.com/attachments/718097267621363744/746322004814331994/SoulEVMax.png",
    "racehud699": "",

    "333TopSpeed": 94,
    "3330to60": 9.0,
    "333Handling": 69,

    "666TopSpeed": 98,
    "6660to60": 8.3,
    "666Handling": 72,

    "969TopSpeed": 102,
    "9690to60": 7.7,
    "969Handling": 74
}