{
    "packName": "5x Perf Tyre SUV Elite Pack",
    "description": "The normal pack of 5 Rare or Higher Performance Tyre SUV cards",
    "repetition": 5,
    "pack": "https://file.garden/ZSrBMiDRyR84aPJp/PackArt/ElitePack.png",
    "filter": {
        "tyreType": "Performance",
        "bodyStyle": "SUV"
    },
    "packSequence": [
        {
            "rare": 73,
            "epic": 20,
            "exotic": 6,
            "legendary": 1
        },
        {
            "rare": 73,
            "epic": 20,
            "exotic": 6,
            "legendary": 1
        },
        {
            "rare": 73,
            "epic": 20,
            "exotic": 6,
            "legendary": 1
        },
        {
            "rare": 73,
            "epic": 20,
            "exotic": 6,
            "legendary": 1
        },
        {
            "rare": 73,
            "epic": 20,
            "exotic": 6,
            "legendary": 1
        }
    ]
}
