{
    "carID": "c0",
    "cr": 238,
    "make": "Mercedes-Benz",
    "model": "B 200 Sports Tourer Classic",
    "modelYear": 2004,
    "country": "DE",
    "topSpeed": 120,
    "0to60": 9.8,
    "handling": 70,
    "driveType": "FWD",
    "tyreType": "Standard",
    "tags": ["Full Throttle"],
    "weight": 1345,
    "gc": "Low",
    "seatCount": 5,
    "bodyStyle": "Hatchback",
    "tcs": true,
    "abs": true,
    "enginePos": "Front",
    "fuelType": "Petrol",
    "mra": 51.69,
    "ola": 67.1,
    "description": "",
    "racehud": "https://file.garden/aFBkIPmb4DlYDcyR/Cars/0in/Mercedes-BenzB200SportsTourerClassic(2004).png",
    "creator": "Pfugs",
    "hiddenTag": [""],
    "cardType": ["Normal"]
}